doc2txt/__init__.py
doc2txt/converter.py
doc2txt/bin/antiword/00README.WIN
doc2txt/bin/antiword/8859-1.txt
doc2txt/bin/antiword/8859-10.txt
doc2txt/bin/antiword/8859-11.txt
doc2txt/bin/antiword/8859-13.txt
doc2txt/bin/antiword/8859-14.txt
doc2txt/bin/antiword/8859-15.txt
doc2txt/bin/antiword/8859-16.txt
doc2txt/bin/antiword/8859-2.txt
doc2txt/bin/antiword/8859-3.txt
doc2txt/bin/antiword/8859-4.txt
doc2txt/bin/antiword/8859-5.txt
doc2txt/bin/antiword/8859-6.txt
doc2txt/bin/antiword/8859-7.txt
doc2txt/bin/antiword/8859-8.txt
doc2txt/bin/antiword/8859-9.txt
doc2txt/bin/antiword/Default
doc2txt/bin/antiword/Example
doc2txt/bin/antiword/MacCyrillic.txt
doc2txt/bin/antiword/MacRoman.txt
doc2txt/bin/antiword/UTF-8.txt
doc2txt/bin/antiword/Unicode01
doc2txt/bin/antiword/Unicode15
doc2txt/bin/antiword/antiword
doc2txt/bin/antiword/antiword.exe
doc2txt/bin/antiword/cp1250.txt
doc2txt/bin/antiword/cp1251.txt
doc2txt/bin/antiword/cp1252.txt
doc2txt/bin/antiword/cp437.txt
doc2txt/bin/antiword/cp850.txt
doc2txt/bin/antiword/cp852.txt
doc2txt/bin/antiword/cp862.txt
doc2txt/bin/antiword/cp864.txt
doc2txt/bin/antiword/cp866.txt
doc2txt/bin/antiword/fontnames
doc2txt/bin/antiword/fontnames.rus
doc2txt/bin/antiword/koi8-r.txt
doc2txt/bin/antiword/koi8-u.txt
doc2txt/bin/antiword/roman.txt
doc2txt/bin/antiword/Docs/COPYING
doc2txt/bin/antiword/Docs/ChangeLog
doc2txt/bin/antiword/Docs/Emacs
doc2txt/bin/antiword/Docs/Exmh
doc2txt/bin/antiword/Docs/FAQ
doc2txt/bin/antiword/Docs/History
doc2txt/bin/antiword/Docs/Mozilla
doc2txt/bin/antiword/Docs/Mutt
doc2txt/bin/antiword/Docs/Netscape
doc2txt/bin/antiword/Docs/QandA
doc2txt/bin/antiword/Docs/ReadMe
doc2txt/bin/antiword/Docs/antiword.1
doc2txt/bin/antiword/Docs/antiword.man
doc2txt/bin/antiword/Docs/antiword.old.php
doc2txt/bin/antiword/Docs/antiword.php
doc2txt/bin/antiword/Docs/testdoc.doc
doc2txt_antiword-0.1.3.dist-info/METADATA
doc2txt_antiword-0.1.3.dist-info/WHEEL
doc2txt_antiword-0.1.3.dist-info/top_level.txt
doc2txt_antiword-0.1.3.dist-info/RECORD
