Metadata-Version: 2.1
Name: doc2txt-antiword
Version: 0.1.3
Summary: A Python package to convert .doc files to .txt using the Antiword binary.
Home-page: https://github.com/Bhola-kumar/doc2txt-py
Author: Bhola Kumar
Author-email: bholak993@example.com
Classifier: Programming Language :: Python :: 3
Classifier: License :: OSI Approved :: MIT License
Classifier: Operating System :: OS Independent
Requires-Python: >=3.6
